pyzernike/__init__.py
pyzernike/__main__.py
pyzernike/__version__.py
pyzernike/cartesian_to_elliptic_annulus.py
pyzernike/radial_display.py
pyzernike/radial_polynomial.py
pyzernike/radial_symbolic.py
pyzernike/xy_zernike_polynomial.py
pyzernike/xy_zernike_polynomial_up_to_order.py
pyzernike/zernike_display.py
pyzernike/zernike_index_to_order.py
pyzernike/zernike_order_to_index.py
pyzernike/zernike_polynomial.py
pyzernike/zernike_polynomial_up_to_order.py
pyzernike/zernike_symbolic.py
pyzernike/core/__init__.py
pyzernike/core/core_cartesian_to_elliptic_annulus.py
pyzernike/core/core_corresponding_signed_integer_type.py
pyzernike/core/core_create_precomputing_terms.py
pyzernike/core/core_display.py
pyzernike/core/core_polynomial.py
pyzernike/core/core_symbolic.py
pyzernike/resources/Navarro and al. Generalization of Zernike polynomials for regular portions of circles and ellipses.pdf
pyzernike/resources/__init__.py
pyzernike/resources/elliptic_annulus_domain.png
pyzernike/resources/radial_display.png
pyzernike/resources/zernike_cos.png
pyzernike/resources/zernike_display.png
pyzernike/resources/zernike_radial.png
pyzernike/resources/zernike_sin.png
pyzernike_polynomials-2.3.1.dist-info/licenses/LICENSE
pyzernike_polynomials-2.3.1.dist-info/METADATA
pyzernike_polynomials-2.3.1.dist-info/WHEEL
pyzernike_polynomials-2.3.1.dist-info/entry_points.txt
pyzernike_polynomials-2.3.1.dist-info/top_level.txt
pyzernike_polynomials-2.3.1.dist-info/RECORD
