Metadata-Version: 2.4
Name: pyzernike-polynomials
Version: 2.3.1
Summary: Zernike polynomials computation and visualization.
Author-email: Artezaru <artezaru.github@proton.me>
License: Copyright 2025 Artezaru
Project-URL: Homepage, https://github.com/Artezaru/pyzernike
Project-URL: Documentation, https://Artezaru.github.io/pyzernike
Project-URL: Source, https://github.com/Artezaru/pyzernike
Project-URL: Tracker, https://github.com/Artezaru/pyzernike/issues
Classifier: Programming Language :: Python :: 3
Classifier: License :: OSI Approved :: Apache Software License
Classifier: Operating System :: OS Independent
Requires-Python: >=3.10
License-File: LICENSE
Requires-Dist: numpy>=1.24.0
Requires-Dist: scipy>=1.10.0
Requires-Dist: matplotlib>=3.7.0
Requires-Dist: sympy>=1.12
Provides-Extra: dev
Requires-Dist: sphinx; extra == "dev"
Requires-Dist: pydata-sphinx-theme; extra == "dev"
Requires-Dist: numpydoc; extra == "dev"
Requires-Dist: pytest; extra == "dev"
Requires-Dist: pytest-cov; extra == "dev"
Requires-Dist: bumpver; extra == "dev"
Requires-Dist: twine; extra == "dev"
Requires-Dist: wheel; extra == "dev"
Requires-Dist: build; extra == "dev"
Requires-Dist: setuptools; extra == "dev"
Requires-Dist: setuptools-scm; extra == "dev"
Dynamic: license-file
